asyncssh/__init__.py
asyncssh/agent.py
asyncssh/agent_unix.py
asyncssh/agent_win32.py
asyncssh/asn1.py
asyncssh/auth.py
asyncssh/auth_keys.py
asyncssh/channel.py
asyncssh/client.py
asyncssh/compression.py
asyncssh/config.py
asyncssh/connection.py
asyncssh/constants.py
asyncssh/dsa.py
asyncssh/ecdsa.py
asyncssh/eddsa.py
asyncssh/editor.py
asyncssh/encryption.py
asyncssh/forward.py
asyncssh/gss.py
asyncssh/gss_unix.py
asyncssh/gss_win32.py
asyncssh/kex.py
asyncssh/kex_dh.py
asyncssh/kex_rsa.py
asyncssh/keysign.py
asyncssh/known_hosts.py
asyncssh/listener.py
asyncssh/logging.py
asyncssh/mac.py
asyncssh/misc.py
asyncssh/packet.py
asyncssh/pattern.py
asyncssh/pbe.py
asyncssh/pkcs11.py
asyncssh/process.py
asyncssh/public_key.py
asyncssh/py.typed
asyncssh/rsa.py
asyncssh/saslprep.py
asyncssh/scp.py
asyncssh/server.py
asyncssh/session.py
asyncssh/sftp.py
asyncssh/sk.py
asyncssh/sk_ecdsa.py
asyncssh/sk_eddsa.py
asyncssh/socks.py
asyncssh/stream.py
asyncssh/subprocess.py
asyncssh/tuntap.py
asyncssh/version.py
asyncssh/x11.py
asyncssh/crypto/__init__.py
asyncssh/crypto/chacha.py
asyncssh/crypto/cipher.py
asyncssh/crypto/dh.py
asyncssh/crypto/dsa.py
asyncssh/crypto/ec.py
asyncssh/crypto/ec_params.py
asyncssh/crypto/ed.py
asyncssh/crypto/kdf.py
asyncssh/crypto/misc.py
asyncssh/crypto/pq.py
asyncssh/crypto/rsa.py
asyncssh/crypto/sntrup.py
asyncssh/crypto/umac.py
asyncssh/crypto/x509.py
asyncssh-2.18.0.dist-info/LICENSE
asyncssh-2.18.0.dist-info/METADATA
asyncssh-2.18.0.dist-info/WHEEL
asyncssh-2.18.0.dist-info/top_level.txt
asyncssh-2.18.0.dist-info/RECORD
